pandusx2/__init__.py
pandusx2/main.py
pandusx2-0.1.33.dist-info/METADATA
pandusx2-0.1.33.dist-info/WHEEL
pandusx2-0.1.33.dist-info/top_level.txt
pandusx2-0.1.33.dist-info/RECORD
