Metadata-Version: 2.4
Name: pandusx2
Version: 0.1.33
Summary: Pandus package for koding sma
Author: Your Name
Requires-Python: >=3.6
Dynamic: author
Dynamic: requires-python
Dynamic: summary
